{"breadcrumb_path":"/halfdotnet/toc.json","search.ms_sitename":"Docs","search.ms_docsetname":"halfdotnet","version":0,"locale":"en-us","site_name":"Docs","search.ms_product":"MSDN","depot_name":"MSDN.halfdotnet","ref_skeleton_gitcommit":"https://github.com/TianqiZhang/ECMA2YamlTestRepo/blob/1953e5bf3b3df5c71a159a322e33cc682ce4add9/halfdotnet/System.Activities.Presentation.View/System.Activities.Presentation.View.ExpressionTextBox.yml","original_ref_skeleton_git_url":"https://github.com/TianqiZhang/ECMA2YamlTestRepo/blob/migration/halfdotnet/System.Activities.Presentation.View/System.Activities.Presentation.View.ExpressionTextBox.yml","open_to_public_contributors":true,"api_name":["System.Activities.Presentation.View.ExpressionTextBox","System.Activities.Presentation.View.ExpressionTextBox..ctor","System.Activities.Presentation.View.ExpressionTextBox.AcceptsReturn","System.Activities.Presentation.View.ExpressionTextBox.AcceptsReturnProperty","System.Activities.Presentation.View.ExpressionTextBox.AcceptsTab","System.Activities.Presentation.View.ExpressionTextBox.AcceptsTabProperty","System.Activities.Presentation.View.ExpressionTextBox.BeginEdit","System.Activities.Presentation.View.ExpressionTextBox.CompleteWordCommand","System.Activities.Presentation.View.ExpressionTextBox.DecreaseFilterLevelCommand","System.Activities.Presentation.View.ExpressionTextBox.DefaultValue","System.Activities.Presentation.View.ExpressionTextBox.DefaultValueProperty","System.Activities.Presentation.View.ExpressionTextBox.EditorLostLogicalFocus","System.Activities.Presentation.View.ExpressionTextBox.add_EditorLostLogicalFocus","System.Activities.Presentation.View.ExpressionTextBox.remove_EditorLostLogicalFocus","System.Activities.Presentation.View.ExpressionTextBox.EditorLostLogicalFocusEvent","System.Activities.Presentation.View.ExpressionTextBox.ExplicitCommit","System.Activities.Presentation.View.ExpressionTextBox.ExplicitCommitProperty","System.Activities.Presentation.View.ExpressionTextBox.Expression","System.Activities.Presentation.View.ExpressionTextBox.ExpressionActivityEditor","System.Activities.Presentation.View.ExpressionTextBox.ExpressionActivityEditorOptionName","System.Activities.Presentation.View.ExpressionTextBox.ExpressionActivityEditorProperty","System.Activities.Presentation.View.ExpressionTextBox.ExpressionEditorService","System.Activities.Presentation.View.ExpressionTextBox.ExpressionProperty","System.Activities.Presentation.View.ExpressionTextBox.ExpressionType","System.Activities.Presentation.View.ExpressionTextBox.ExpressionTypeProperty","System.Activities.Presentation.View.ExpressionTextBox.GlobalIntellisenseCommand","System.Activities.Presentation.View.ExpressionTextBox.HintText","System.Activities.Presentation.View.ExpressionTextBox.HintTextProperty","System.Activities.Presentation.View.ExpressionTextBox.HorizontalScrollBarVisibility","System.Activities.Presentation.View.ExpressionTextBox.HorizontalScrollBarVisibilityProperty","System.Activities.Presentation.View.ExpressionTextBox.IncreaseFilterLevelCommand","System.Activities.Presentation.View.ExpressionTextBox.InitializeComponent","System.Activities.Presentation.View.ExpressionTextBox.IsReadOnly","System.Activities.Presentation.View.ExpressionTextBox.IsReadOnlyProperty","System.Activities.Presentation.View.ExpressionTextBox.IsSupportedExpression","System.Activities.Presentation.View.ExpressionTextBox.IsSupportedExpressionProperty","System.Activities.Presentation.View.ExpressionTextBox.MaxLines","System.Activities.Presentation.View.ExpressionTextBox.MaxLinesProperty","System.Activities.Presentation.View.ExpressionTextBox.MinLines","System.Activities.Presentation.View.ExpressionTextBox.MinLinesProperty","System.Activities.Presentation.View.ExpressionTextBox.OnCreateAutomationPeer","System.Activities.Presentation.View.ExpressionTextBox.OnInitialized","System.Activities.Presentation.View.ExpressionTextBox.OnPropertyChanged","System.Activities.Presentation.View.ExpressionTextBox.OwnerActivity","System.Activities.Presentation.View.ExpressionTextBox.OwnerActivityProperty","System.Activities.Presentation.View.ExpressionTextBox.ParameterInfoCommand","System.Activities.Presentation.View.ExpressionTextBox.PathToArgument","System.Activities.Presentation.View.ExpressionTextBox.PathToArgumentProperty","System.Activities.Presentation.View.ExpressionTextBox.QuickInfoCommand","System.Activities.Presentation.View.ExpressionTextBox.RegisterExpressionActivityEditor","System.Activities.Presentation.View.ExpressionTextBox.System.Windows.Markup.IComponentConnector.Connect","System.Activities.Presentation.View.ExpressionTextBox.UseLocationExpression","System.Activities.Presentation.View.ExpressionTextBox.UseLocationExpressionProperty","System.Activities.Presentation.View.ExpressionTextBox.VerticalScrollBarVisibility","System.Activities.Presentation.View.ExpressionTextBox.VerticalScrollBarVisibilityProperty"],"api_location":["System.Activities.Presentation.dll"],"topic_type":["apiref"],"api_type":["Assembly"],"f1_keywords":["System.Activities.Presentation.View.ExpressionTextBox","System::Activities::Presentation::View::ExpressionTextBox","System.Activities.Presentation.View.ExpressionTextBox.#ctor","System::Activities::Presentation::View::ExpressionTextBox::#ctor","System.Activities.Presentation.View.ExpressionTextBox.AcceptsReturn","System::Activities::Presentation::View::ExpressionTextBox::AcceptsReturn","System.Activities.Presentation.View.ExpressionTextBox.AcceptsReturnProperty","System::Activities::Presentation::View::ExpressionTextBox::AcceptsReturnProperty","System.Activities.Presentation.View.ExpressionTextBox.AcceptsTab","System::Activities::Presentation::View::ExpressionTextBox::AcceptsTab","System.Activities.Presentation.View.ExpressionTextBox.AcceptsTabProperty","System::Activities::Presentation::View::ExpressionTextBox::AcceptsTabProperty","System.Activities.Presentation.View.ExpressionTextBox.BeginEdit","System::Activities::Presentation::View::ExpressionTextBox::BeginEdit","System.Activities.Presentation.View.ExpressionTextBox.CompleteWordCommand","System::Activities::Presentation::View::ExpressionTextBox::CompleteWordCommand","System.Activities.Presentation.View.ExpressionTextBox.DecreaseFilterLevelCommand","System::Activities::Presentation::View::ExpressionTextBox::DecreaseFilterLevelCommand","System.Activities.Presentation.View.ExpressionTextBox.DefaultValue","System::Activities::Presentation::View::ExpressionTextBox::DefaultValue","System.Activities.Presentation.View.ExpressionTextBox.DefaultValueProperty","System::Activities::Presentation::View::ExpressionTextBox::DefaultValueProperty","System.Activities.Presentation.View.ExpressionTextBox.EditorLostLogicalFocus","System::Activities::Presentation::View::ExpressionTextBox::EditorLostLogicalFocus","System.Activities.Presentation.View.ExpressionTextBox.EditorLostLogicalFocusEvent","System::Activities::Presentation::View::ExpressionTextBox::EditorLostLogicalFocusEvent","System.Activities.Presentation.View.ExpressionTextBox.ExplicitCommit","System::Activities::Presentation::View::ExpressionTextBox::ExplicitCommit","System.Activities.Presentation.View.ExpressionTextBox.ExplicitCommitProperty","System::Activities::Presentation::View::ExpressionTextBox::ExplicitCommitProperty","System.Activities.Presentation.View.ExpressionTextBox.Expression","System::Activities::Presentation::View::ExpressionTextBox::Expression","System.Activities.Presentation.View.ExpressionTextBox.ExpressionActivityEditor","System::Activities::Presentation::View::ExpressionTextBox::ExpressionActivityEditor","System.Activities.Presentation.View.ExpressionTextBox.ExpressionActivityEditorOptionName","System::Activities::Presentation::View::ExpressionTextBox::ExpressionActivityEditorOptionName","System.Activities.Presentation.View.ExpressionTextBox.ExpressionActivityEditorProperty","System::Activities::Presentation::View::ExpressionTextBox::ExpressionActivityEditorProperty","System.Activities.Presentation.View.ExpressionTextBox.ExpressionEditorService","System::Activities::Presentation::View::ExpressionTextBox::ExpressionEditorService","System.Activities.Presentation.View.ExpressionTextBox.ExpressionProperty","System::Activities::Presentation::View::ExpressionTextBox::ExpressionProperty","System.Activities.Presentation.View.ExpressionTextBox.ExpressionType","System::Activities::Presentation::View::ExpressionTextBox::ExpressionType","System.Activities.Presentation.View.ExpressionTextBox.ExpressionTypeProperty","System::Activities::Presentation::View::ExpressionTextBox::ExpressionTypeProperty","System.Activities.Presentation.View.ExpressionTextBox.GlobalIntellisenseCommand","System::Activities::Presentation::View::ExpressionTextBox::GlobalIntellisenseCommand","System.Activities.Presentation.View.ExpressionTextBox.HintText","System::Activities::Presentation::View::ExpressionTextBox::HintText","System.Activities.Presentation.View.ExpressionTextBox.HintTextProperty","System::Activities::Presentation::View::ExpressionTextBox::HintTextProperty","System.Activities.Presentation.View.ExpressionTextBox.HorizontalScrollBarVisibility","System::Activities::Presentation::View::ExpressionTextBox::HorizontalScrollBarVisibility","System.Activities.Presentation.View.ExpressionTextBox.HorizontalScrollBarVisibilityProperty","System::Activities::Presentation::View::ExpressionTextBox::HorizontalScrollBarVisibilityProperty","System.Activities.Presentation.View.ExpressionTextBox.IncreaseFilterLevelCommand","System::Activities::Presentation::View::ExpressionTextBox::IncreaseFilterLevelCommand","System.Activities.Presentation.View.ExpressionTextBox.InitializeComponent","System::Activities::Presentation::View::ExpressionTextBox::InitializeComponent","System.Activities.Presentation.View.ExpressionTextBox.IsReadOnly","System::Activities::Presentation::View::ExpressionTextBox::IsReadOnly","System.Activities.Presentation.View.ExpressionTextBox.IsReadOnlyProperty","System::Activities::Presentation::View::ExpressionTextBox::IsReadOnlyProperty","System.Activities.Presentation.View.ExpressionTextBox.IsSupportedExpression","System::Activities::Presentation::View::ExpressionTextBox::IsSupportedExpression","System.Activities.Presentation.View.ExpressionTextBox.IsSupportedExpressionProperty","System::Activities::Presentation::View::ExpressionTextBox::IsSupportedExpressionProperty","System.Activities.Presentation.View.ExpressionTextBox.MaxLines","System::Activities::Presentation::View::ExpressionTextBox::MaxLines","System.Activities.Presentation.View.ExpressionTextBox.MaxLinesProperty","System::Activities::Presentation::View::ExpressionTextBox::MaxLinesProperty","System.Activities.Presentation.View.ExpressionTextBox.MinLines","System::Activities::Presentation::View::ExpressionTextBox::MinLines","System.Activities.Presentation.View.ExpressionTextBox.MinLinesProperty","System::Activities::Presentation::View::ExpressionTextBox::MinLinesProperty","System.Activities.Presentation.View.ExpressionTextBox.OnCreateAutomationPeer","System::Activities::Presentation::View::ExpressionTextBox::OnCreateAutomationPeer","System.Activities.Presentation.View.ExpressionTextBox.OnInitialized","System::Activities::Presentation::View::ExpressionTextBox::OnInitialized","System.Activities.Presentation.View.ExpressionTextBox.OnPropertyChanged","System::Activities::Presentation::View::ExpressionTextBox::OnPropertyChanged","System.Activities.Presentation.View.ExpressionTextBox.OwnerActivity","System::Activities::Presentation::View::ExpressionTextBox::OwnerActivity","System.Activities.Presentation.View.ExpressionTextBox.OwnerActivityProperty","System::Activities::Presentation::View::ExpressionTextBox::OwnerActivityProperty","System.Activities.Presentation.View.ExpressionTextBox.ParameterInfoCommand","System::Activities::Presentation::View::ExpressionTextBox::ParameterInfoCommand","System.Activities.Presentation.View.ExpressionTextBox.PathToArgument","System::Activities::Presentation::View::ExpressionTextBox::PathToArgument","System.Activities.Presentation.View.ExpressionTextBox.PathToArgumentProperty","System::Activities::Presentation::View::ExpressionTextBox::PathToArgumentProperty","System.Activities.Presentation.View.ExpressionTextBox.QuickInfoCommand","System::Activities::Presentation::View::ExpressionTextBox::QuickInfoCommand","System.Activities.Presentation.View.ExpressionTextBox.RegisterExpressionActivityEditor","System::Activities::Presentation::View::ExpressionTextBox::RegisterExpressionActivityEditor","System.Activities.Presentation.View.ExpressionTextBox.System#Windows#Markup#IComponentConnector#Connect","System::Activities::Presentation::View::ExpressionTextBox::System#Windows#Markup#IComponentConnector#Connect","System.Activities.Presentation.View.ExpressionTextBox.UseLocationExpression","System::Activities::Presentation::View::ExpressionTextBox::UseLocationExpression","System.Activities.Presentation.View.ExpressionTextBox.UseLocationExpressionProperty","System::Activities::Presentation::View::ExpressionTextBox::UseLocationExpressionProperty","System.Activities.Presentation.View.ExpressionTextBox.VerticalScrollBarVisibility","System::Activities::Presentation::View::ExpressionTextBox::VerticalScrollBarVisibility","System.Activities.Presentation.View.ExpressionTextBox.VerticalScrollBarVisibilityProperty","System::Activities::Presentation::View::ExpressionTextBox::VerticalScrollBarVisibilityProperty"],"dev_langs":["csharp"],"updated_at":"2017-02-16 06:36 AM","document_id":"2166f2da-31f9-1e24-db08-7bbe8deaaf69","layout":"Reference","pagetype":"Reference","title":"ExpressionTextBox class | Microsoft Docs","toc_asset_id":"toc.json","toc_rel":"../toc.json","platforms":["net-11","net-20","netcore-10"],"content_git_url":"","source_url":"","ms.assetid":"System.Activities.Presentation.View.ExpressionTextBox","canonical_url":"https://ppe.docs.microsoft.com/en-us/halfdotnet/system.activities.presentation.view/system.activities.presentation.view.expressiontextbox","is_dynamic_rendering":false,"content_type":"text/html","publish_version":"{\"opbuild.templates.docs\":\"1.28.0-alpha-081-g501ae23\",\"commit_id\":\"c463338a38ee0cf171b48332bb4325e618b23055\",\"branch\":\"migration\",\"opbuild.scripts\":\"1.28.0-alpha-081-g501ae23\",\"opbuild.htmltopdftool\":\"1.28.0-alpha-081-g501ae23\",\"opbuild.gitcontributorinformationresolver\":\"1.28.0-alpha-081-g501ae23\",\"opbuild_service\":\"1.28.81.0\",\"docfx.console\":\"2.13.0-alpha-1199-g3fa481b\",\"opbuild.resolvedependencyconsole\":\"1.28.0-alpha-081-g501ae23\",\"opbuild.schemavalidationconsole\":\"1.28.0-alpha-081-g501ae23\",\"opbuild.redirectionresolver\":\"1.28.0-alpha-081-g501ae23\",\"opbuild.templates.intellisense\":\"1.28.0-alpha-081-g501ae23\",\"dependencies\":[{\"branch\":\"master\",\"path\":\"_themes\",\"url\":\"https://github.com/Microsoft/templates.docs.msft\",\"commit_id\":\"be77cfdb101840a69eabbfa9cdb134e565d77113\",\"opbuild.templates.common\":\"1.28.0-alpha-081-g501ae23\"}]}"}