{"breadcrumb_path":"/halfdotnet/toc.json","search.ms_sitename":"Docs","search.ms_docsetname":"halfdotnet","version":0,"locale":"en-us","site_name":"Docs","search.ms_product":"MSDN","depot_name":"MSDN.halfdotnet","ref_skeleton_gitcommit":"https://github.com/TianqiZhang/ECMA2YamlTestRepo/blob/1953e5bf3b3df5c71a159a322e33cc682ce4add9/halfdotnet/System.Runtime.CompilerServices/System.Runtime.CompilerServices.ReadOnlyCollectionBuilder-1.yml","original_ref_skeleton_git_url":"https://github.com/TianqiZhang/ECMA2YamlTestRepo/blob/migration/halfdotnet/System.Runtime.CompilerServices/System.Runtime.CompilerServices.ReadOnlyCollectionBuilder-1.yml","open_to_public_contributors":true,"api_name":["System.Runtime.CompilerServices.ReadOnlyCollectionBuilder<T>","System.Runtime.CompilerServices.ReadOnlyCollectionBuilder<T>..ctor","System.Runtime.CompilerServices.ReadOnlyCollectionBuilder<T>.Add","System.Runtime.CompilerServices.ReadOnlyCollectionBuilder<T>.Capacity","System.Runtime.CompilerServices.ReadOnlyCollectionBuilder<T>.Clear","System.Runtime.CompilerServices.ReadOnlyCollectionBuilder<T>.Contains","System.Runtime.CompilerServices.ReadOnlyCollectionBuilder<T>.CopyTo","System.Runtime.CompilerServices.ReadOnlyCollectionBuilder<T>.Count","System.Runtime.CompilerServices.ReadOnlyCollectionBuilder<T>.GetEnumerator","System.Runtime.CompilerServices.ReadOnlyCollectionBuilder<T>.IndexOf","System.Runtime.CompilerServices.ReadOnlyCollectionBuilder<T>.Insert","System.Runtime.CompilerServices.ReadOnlyCollectionBuilder<T>.Item","System.Runtime.CompilerServices.ReadOnlyCollectionBuilder<T>.Remove","System.Runtime.CompilerServices.ReadOnlyCollectionBuilder<T>.RemoveAt","System.Runtime.CompilerServices.ReadOnlyCollectionBuilder<T>.Reverse","System.Runtime.CompilerServices.ReadOnlyCollectionBuilder<T>.System.Collections.Generic.ICollection","System.Runtime.CompilerServices.ReadOnlyCollectionBuilder<T>.System.Collections.ICollection.CopyTo","System.Runtime.CompilerServices.ReadOnlyCollectionBuilder<T>.System.Collections.ICollection.IsSynchronized","System.Runtime.CompilerServices.ReadOnlyCollectionBuilder<T>.System.Collections.ICollection.SyncRoot","System.Runtime.CompilerServices.ReadOnlyCollectionBuilder<T>.System.Collections.IEnumerable.GetEnumerator","System.Runtime.CompilerServices.ReadOnlyCollectionBuilder<T>.System.Collections.IList.Add","System.Runtime.CompilerServices.ReadOnlyCollectionBuilder<T>.System.Collections.IList.Contains","System.Runtime.CompilerServices.ReadOnlyCollectionBuilder<T>.System.Collections.IList.IndexOf","System.Runtime.CompilerServices.ReadOnlyCollectionBuilder<T>.System.Collections.IList.Insert","System.Runtime.CompilerServices.ReadOnlyCollectionBuilder<T>.System.Collections.IList.IsFixedSize","System.Runtime.CompilerServices.ReadOnlyCollectionBuilder<T>.System.Collections.IList.IsReadOnly","System.Runtime.CompilerServices.ReadOnlyCollectionBuilder<T>.System.Collections.IList.Item","System.Runtime.CompilerServices.ReadOnlyCollectionBuilder<T>.System.Collections.IList.Remove","System.Runtime.CompilerServices.ReadOnlyCollectionBuilder<T>.ToArray","System.Runtime.CompilerServices.ReadOnlyCollectionBuilder<T>.ToReadOnlyCollection"],"api_location":["System.Core.dll"],"topic_type":["apiref"],"api_type":["Assembly"],"f1_keywords":["System.Runtime.CompilerServices.ReadOnlyCollectionBuilder`1","System::Runtime::CompilerServices::ReadOnlyCollectionBuilder`1","System.Runtime.CompilerServices.ReadOnlyCollectionBuilder`1.#ctor","System::Runtime::CompilerServices::ReadOnlyCollectionBuilder`1::#ctor","System.Runtime.CompilerServices.ReadOnlyCollectionBuilder`1.Add","System::Runtime::CompilerServices::ReadOnlyCollectionBuilder`1::Add","System.Runtime.CompilerServices.ReadOnlyCollectionBuilder`1.Capacity","System::Runtime::CompilerServices::ReadOnlyCollectionBuilder`1::Capacity","System.Runtime.CompilerServices.ReadOnlyCollectionBuilder`1.Clear","System::Runtime::CompilerServices::ReadOnlyCollectionBuilder`1::Clear","System.Runtime.CompilerServices.ReadOnlyCollectionBuilder`1.Contains","System::Runtime::CompilerServices::ReadOnlyCollectionBuilder`1::Contains","System.Runtime.CompilerServices.ReadOnlyCollectionBuilder`1.CopyTo","System::Runtime::CompilerServices::ReadOnlyCollectionBuilder`1::CopyTo","System.Runtime.CompilerServices.ReadOnlyCollectionBuilder`1.Count","System::Runtime::CompilerServices::ReadOnlyCollectionBuilder`1::Count","System.Runtime.CompilerServices.ReadOnlyCollectionBuilder`1.GetEnumerator","System::Runtime::CompilerServices::ReadOnlyCollectionBuilder`1::GetEnumerator","System.Runtime.CompilerServices.ReadOnlyCollectionBuilder`1.IndexOf","System::Runtime::CompilerServices::ReadOnlyCollectionBuilder`1::IndexOf","System.Runtime.CompilerServices.ReadOnlyCollectionBuilder`1.Insert","System::Runtime::CompilerServices::ReadOnlyCollectionBuilder`1::Insert","System.Runtime.CompilerServices.ReadOnlyCollectionBuilder`1.Item","System::Runtime::CompilerServices::ReadOnlyCollectionBuilder`1::Item","System.Runtime.CompilerServices.ReadOnlyCollectionBuilder`1.Remove","System::Runtime::CompilerServices::ReadOnlyCollectionBuilder`1::Remove","System.Runtime.CompilerServices.ReadOnlyCollectionBuilder`1.RemoveAt","System::Runtime::CompilerServices::ReadOnlyCollectionBuilder`1::RemoveAt","System.Runtime.CompilerServices.ReadOnlyCollectionBuilder`1.Reverse","System::Runtime::CompilerServices::ReadOnlyCollectionBuilder`1::Reverse","System.Runtime.CompilerServices.ReadOnlyCollectionBuilder`1.System#Collections#Generic#ICollection{T}#IsReadOnly","System::Runtime::CompilerServices::ReadOnlyCollectionBuilder`1::System#Collections#Generic#ICollection{T}#IsReadOnly","System.Runtime.CompilerServices.ReadOnlyCollectionBuilder`1.System#Collections#ICollection#CopyTo","System::Runtime::CompilerServices::ReadOnlyCollectionBuilder`1::System#Collections#ICollection#CopyTo","System.Runtime.CompilerServices.ReadOnlyCollectionBuilder`1.System#Collections#ICollection#IsSynchronized","System::Runtime::CompilerServices::ReadOnlyCollectionBuilder`1::System#Collections#ICollection#IsSynchronized","System.Runtime.CompilerServices.ReadOnlyCollectionBuilder`1.System#Collections#ICollection#SyncRoot","System::Runtime::CompilerServices::ReadOnlyCollectionBuilder`1::System#Collections#ICollection#SyncRoot","System.Runtime.CompilerServices.ReadOnlyCollectionBuilder`1.System#Collections#IEnumerable#GetEnumerator","System::Runtime::CompilerServices::ReadOnlyCollectionBuilder`1::System#Collections#IEnumerable#GetEnumerator","System.Runtime.CompilerServices.ReadOnlyCollectionBuilder`1.System#Collections#IList#Add","System::Runtime::CompilerServices::ReadOnlyCollectionBuilder`1::System#Collections#IList#Add","System.Runtime.CompilerServices.ReadOnlyCollectionBuilder`1.System#Collections#IList#Contains","System::Runtime::CompilerServices::ReadOnlyCollectionBuilder`1::System#Collections#IList#Contains","System.Runtime.CompilerServices.ReadOnlyCollectionBuilder`1.System#Collections#IList#IndexOf","System::Runtime::CompilerServices::ReadOnlyCollectionBuilder`1::System#Collections#IList#IndexOf","System.Runtime.CompilerServices.ReadOnlyCollectionBuilder`1.System#Collections#IList#Insert","System::Runtime::CompilerServices::ReadOnlyCollectionBuilder`1::System#Collections#IList#Insert","System.Runtime.CompilerServices.ReadOnlyCollectionBuilder`1.System#Collections#IList#IsFixedSize","System::Runtime::CompilerServices::ReadOnlyCollectionBuilder`1::System#Collections#IList#IsFixedSize","System.Runtime.CompilerServices.ReadOnlyCollectionBuilder`1.System#Collections#IList#IsReadOnly","System::Runtime::CompilerServices::ReadOnlyCollectionBuilder`1::System#Collections#IList#IsReadOnly","System.Runtime.CompilerServices.ReadOnlyCollectionBuilder`1.System#Collections#IList#Item","System::Runtime::CompilerServices::ReadOnlyCollectionBuilder`1::System#Collections#IList#Item","System.Runtime.CompilerServices.ReadOnlyCollectionBuilder`1.System#Collections#IList#Remove","System::Runtime::CompilerServices::ReadOnlyCollectionBuilder`1::System#Collections#IList#Remove","System.Runtime.CompilerServices.ReadOnlyCollectionBuilder`1.ToArray","System::Runtime::CompilerServices::ReadOnlyCollectionBuilder`1::ToArray","System.Runtime.CompilerServices.ReadOnlyCollectionBuilder`1.ToReadOnlyCollection","System::Runtime::CompilerServices::ReadOnlyCollectionBuilder`1::ToReadOnlyCollection"],"dev_langs":["csharp"],"updated_at":"2017-02-16 06:36 AM","document_id":"f23c5410-44b6-9d20-75ec-4874152a8e7a","layout":"Reference","pagetype":"Reference","title":"ReadOnlyCollectionBuilder<T> class | Microsoft Docs","toc_asset_id":"toc.json","toc_rel":"../toc.json","platforms":["net-11","net-20","netcore-10"],"content_git_url":"","source_url":"","ms.assetid":"System.Runtime.CompilerServices.ReadOnlyCollectionBuilder`1","canonical_url":"https://ppe.docs.microsoft.com/en-us/halfdotnet/system.runtime.compilerservices/system.runtime.compilerservices.readonlycollectionbuilder-1","is_dynamic_rendering":false,"content_type":"text/html","publish_version":"{\"opbuild.templates.docs\":\"1.28.0-alpha-081-g501ae23\",\"commit_id\":\"c463338a38ee0cf171b48332bb4325e618b23055\",\"branch\":\"migration\",\"opbuild.scripts\":\"1.28.0-alpha-081-g501ae23\",\"opbuild.htmltopdftool\":\"1.28.0-alpha-081-g501ae23\",\"opbuild.gitcontributorinformationresolver\":\"1.28.0-alpha-081-g501ae23\",\"opbuild_service\":\"1.28.81.0\",\"docfx.console\":\"2.13.0-alpha-1199-g3fa481b\",\"opbuild.resolvedependencyconsole\":\"1.28.0-alpha-081-g501ae23\",\"opbuild.schemavalidationconsole\":\"1.28.0-alpha-081-g501ae23\",\"opbuild.redirectionresolver\":\"1.28.0-alpha-081-g501ae23\",\"opbuild.templates.intellisense\":\"1.28.0-alpha-081-g501ae23\",\"dependencies\":[{\"branch\":\"master\",\"path\":\"_themes\",\"url\":\"https://github.com/Microsoft/templates.docs.msft\",\"commit_id\":\"be77cfdb101840a69eabbfa9cdb134e565d77113\",\"opbuild.templates.common\":\"1.28.0-alpha-081-g501ae23\"}]}"}