{"breadcrumb_path":"/halfdotnet/toc.json","search.ms_sitename":"Docs","search.ms_docsetname":"halfdotnet","version":0,"locale":"en-us","site_name":"Docs","search.ms_product":"MSDN","depot_name":"MSDN.halfdotnet","ref_skeleton_gitcommit":"https://github.com/TianqiZhang/ECMA2YamlTestRepo/blob/1953e5bf3b3df5c71a159a322e33cc682ce4add9/halfdotnet/System.Windows.Data/System.Windows.Data.CollectionViewSource.yml","original_ref_skeleton_git_url":"https://github.com/TianqiZhang/ECMA2YamlTestRepo/blob/migration/halfdotnet/System.Windows.Data/System.Windows.Data.CollectionViewSource.yml","open_to_public_contributors":true,"api_name":["System.Windows.Data.CollectionViewSource","System.Windows.Data.CollectionViewSource..ctor","System.Windows.Data.CollectionViewSource.CanChangeLiveFiltering","System.Windows.Data.CollectionViewSource.CanChangeLiveFilteringProperty","System.Windows.Data.CollectionViewSource.CanChangeLiveGrouping","System.Windows.Data.CollectionViewSource.CanChangeLiveGroupingProperty","System.Windows.Data.CollectionViewSource.CanChangeLiveSorting","System.Windows.Data.CollectionViewSource.CanChangeLiveSortingProperty","System.Windows.Data.CollectionViewSource.CollectionViewType","System.Windows.Data.CollectionViewSource.CollectionViewTypeProperty","System.Windows.Data.CollectionViewSource.Culture","System.Windows.Data.CollectionViewSource.DeferRefresh","System.Windows.Data.CollectionViewSource.Filter","System.Windows.Data.CollectionViewSource.add_Filter","System.Windows.Data.CollectionViewSource.remove_Filter","System.Windows.Data.CollectionViewSource.GetDefaultView","System.Windows.Data.CollectionViewSource.GroupDescriptions","System.Windows.Data.CollectionViewSource.IsDefaultView","System.Windows.Data.CollectionViewSource.IsLiveFiltering","System.Windows.Data.CollectionViewSource.IsLiveFilteringProperty","System.Windows.Data.CollectionViewSource.IsLiveFilteringRequested","System.Windows.Data.CollectionViewSource.IsLiveFilteringRequestedProperty","System.Windows.Data.CollectionViewSource.IsLiveGrouping","System.Windows.Data.CollectionViewSource.IsLiveGroupingProperty","System.Windows.Data.CollectionViewSource.IsLiveGroupingRequested","System.Windows.Data.CollectionViewSource.IsLiveGroupingRequestedProperty","System.Windows.Data.CollectionViewSource.IsLiveSorting","System.Windows.Data.CollectionViewSource.IsLiveSortingProperty","System.Windows.Data.CollectionViewSource.IsLiveSortingRequested","System.Windows.Data.CollectionViewSource.IsLiveSortingRequestedProperty","System.Windows.Data.CollectionViewSource.LiveFilteringProperties","System.Windows.Data.CollectionViewSource.LiveGroupingProperties","System.Windows.Data.CollectionViewSource.LiveSortingProperties","System.Windows.Data.CollectionViewSource.OnCollectionViewTypeChanged","System.Windows.Data.CollectionViewSource.OnSourceChanged","System.Windows.Data.CollectionViewSource.ReceiveWeakEvent","System.Windows.Data.CollectionViewSource.SortDescriptions","System.Windows.Data.CollectionViewSource.Source","System.Windows.Data.CollectionViewSource.SourceProperty","System.Windows.Data.CollectionViewSource.System.ComponentModel.ISupportInitialize.BeginInit","System.Windows.Data.CollectionViewSource.System.ComponentModel.ISupportInitialize.EndInit","System.Windows.Data.CollectionViewSource.System.Windows.IWeakEventListener.ReceiveWeakEvent","System.Windows.Data.CollectionViewSource.View","System.Windows.Data.CollectionViewSource.ViewProperty"],"api_location":["PresentationFramework.dll"],"topic_type":["apiref"],"api_type":["Assembly"],"f1_keywords":["System.Windows.Data.CollectionViewSource","System::Windows::Data::CollectionViewSource","System.Windows.Data.CollectionViewSource.#ctor","System::Windows::Data::CollectionViewSource::#ctor","System.Windows.Data.CollectionViewSource.CanChangeLiveFiltering","System::Windows::Data::CollectionViewSource::CanChangeLiveFiltering","System.Windows.Data.CollectionViewSource.CanChangeLiveFilteringProperty","System::Windows::Data::CollectionViewSource::CanChangeLiveFilteringProperty","System.Windows.Data.CollectionViewSource.CanChangeLiveGrouping","System::Windows::Data::CollectionViewSource::CanChangeLiveGrouping","System.Windows.Data.CollectionViewSource.CanChangeLiveGroupingProperty","System::Windows::Data::CollectionViewSource::CanChangeLiveGroupingProperty","System.Windows.Data.CollectionViewSource.CanChangeLiveSorting","System::Windows::Data::CollectionViewSource::CanChangeLiveSorting","System.Windows.Data.CollectionViewSource.CanChangeLiveSortingProperty","System::Windows::Data::CollectionViewSource::CanChangeLiveSortingProperty","System.Windows.Data.CollectionViewSource.CollectionViewType","System::Windows::Data::CollectionViewSource::CollectionViewType","System.Windows.Data.CollectionViewSource.CollectionViewTypeProperty","System::Windows::Data::CollectionViewSource::CollectionViewTypeProperty","System.Windows.Data.CollectionViewSource.Culture","System::Windows::Data::CollectionViewSource::Culture","System.Windows.Data.CollectionViewSource.DeferRefresh","System::Windows::Data::CollectionViewSource::DeferRefresh","System.Windows.Data.CollectionViewSource.Filter","System::Windows::Data::CollectionViewSource::Filter","System.Windows.Data.CollectionViewSource.GetDefaultView","System::Windows::Data::CollectionViewSource::GetDefaultView","System.Windows.Data.CollectionViewSource.GroupDescriptions","System::Windows::Data::CollectionViewSource::GroupDescriptions","System.Windows.Data.CollectionViewSource.IsDefaultView","System::Windows::Data::CollectionViewSource::IsDefaultView","System.Windows.Data.CollectionViewSource.IsLiveFiltering","System::Windows::Data::CollectionViewSource::IsLiveFiltering","System.Windows.Data.CollectionViewSource.IsLiveFilteringProperty","System::Windows::Data::CollectionViewSource::IsLiveFilteringProperty","System.Windows.Data.CollectionViewSource.IsLiveFilteringRequested","System::Windows::Data::CollectionViewSource::IsLiveFilteringRequested","System.Windows.Data.CollectionViewSource.IsLiveFilteringRequestedProperty","System::Windows::Data::CollectionViewSource::IsLiveFilteringRequestedProperty","System.Windows.Data.CollectionViewSource.IsLiveGrouping","System::Windows::Data::CollectionViewSource::IsLiveGrouping","System.Windows.Data.CollectionViewSource.IsLiveGroupingProperty","System::Windows::Data::CollectionViewSource::IsLiveGroupingProperty","System.Windows.Data.CollectionViewSource.IsLiveGroupingRequested","System::Windows::Data::CollectionViewSource::IsLiveGroupingRequested","System.Windows.Data.CollectionViewSource.IsLiveGroupingRequestedProperty","System::Windows::Data::CollectionViewSource::IsLiveGroupingRequestedProperty","System.Windows.Data.CollectionViewSource.IsLiveSorting","System::Windows::Data::CollectionViewSource::IsLiveSorting","System.Windows.Data.CollectionViewSource.IsLiveSortingProperty","System::Windows::Data::CollectionViewSource::IsLiveSortingProperty","System.Windows.Data.CollectionViewSource.IsLiveSortingRequested","System::Windows::Data::CollectionViewSource::IsLiveSortingRequested","System.Windows.Data.CollectionViewSource.IsLiveSortingRequestedProperty","System::Windows::Data::CollectionViewSource::IsLiveSortingRequestedProperty","System.Windows.Data.CollectionViewSource.LiveFilteringProperties","System::Windows::Data::CollectionViewSource::LiveFilteringProperties","System.Windows.Data.CollectionViewSource.LiveGroupingProperties","System::Windows::Data::CollectionViewSource::LiveGroupingProperties","System.Windows.Data.CollectionViewSource.LiveSortingProperties","System::Windows::Data::CollectionViewSource::LiveSortingProperties","System.Windows.Data.CollectionViewSource.OnCollectionViewTypeChanged","System::Windows::Data::CollectionViewSource::OnCollectionViewTypeChanged","System.Windows.Data.CollectionViewSource.OnSourceChanged","System::Windows::Data::CollectionViewSource::OnSourceChanged","System.Windows.Data.CollectionViewSource.ReceiveWeakEvent","System::Windows::Data::CollectionViewSource::ReceiveWeakEvent","System.Windows.Data.CollectionViewSource.SortDescriptions","System::Windows::Data::CollectionViewSource::SortDescriptions","System.Windows.Data.CollectionViewSource.Source","System::Windows::Data::CollectionViewSource::Source","System.Windows.Data.CollectionViewSource.SourceProperty","System::Windows::Data::CollectionViewSource::SourceProperty","System.Windows.Data.CollectionViewSource.System#ComponentModel#ISupportInitialize#BeginInit","System::Windows::Data::CollectionViewSource::System#ComponentModel#ISupportInitialize#BeginInit","System.Windows.Data.CollectionViewSource.System#ComponentModel#ISupportInitialize#EndInit","System::Windows::Data::CollectionViewSource::System#ComponentModel#ISupportInitialize#EndInit","System.Windows.Data.CollectionViewSource.System#Windows#IWeakEventListener#ReceiveWeakEvent","System::Windows::Data::CollectionViewSource::System#Windows#IWeakEventListener#ReceiveWeakEvent","System.Windows.Data.CollectionViewSource.View","System::Windows::Data::CollectionViewSource::View","System.Windows.Data.CollectionViewSource.ViewProperty","System::Windows::Data::CollectionViewSource::ViewProperty"],"dev_langs":["csharp"],"updated_at":"2017-02-16 06:36 AM","document_id":"3783ce7f-fd7f-67d9-c649-bf92a72493c5","layout":"Reference","pagetype":"Reference","title":"CollectionViewSource class | Microsoft Docs","toc_asset_id":"toc.json","toc_rel":"../toc.json","platforms":["net-11","net-20","netcore-10"],"content_git_url":"","source_url":"","ms.assetid":"System.Windows.Data.CollectionViewSource","canonical_url":"https://ppe.docs.microsoft.com/en-us/halfdotnet/system.windows.data/system.windows.data.collectionviewsource","is_dynamic_rendering":false,"content_type":"text/html","publish_version":"{\"opbuild.templates.docs\":\"1.28.0-alpha-081-g501ae23\",\"commit_id\":\"c463338a38ee0cf171b48332bb4325e618b23055\",\"branch\":\"migration\",\"opbuild.scripts\":\"1.28.0-alpha-081-g501ae23\",\"opbuild.htmltopdftool\":\"1.28.0-alpha-081-g501ae23\",\"opbuild.gitcontributorinformationresolver\":\"1.28.0-alpha-081-g501ae23\",\"opbuild_service\":\"1.28.81.0\",\"docfx.console\":\"2.13.0-alpha-1199-g3fa481b\",\"opbuild.resolvedependencyconsole\":\"1.28.0-alpha-081-g501ae23\",\"opbuild.schemavalidationconsole\":\"1.28.0-alpha-081-g501ae23\",\"opbuild.redirectionresolver\":\"1.28.0-alpha-081-g501ae23\",\"opbuild.templates.intellisense\":\"1.28.0-alpha-081-g501ae23\",\"dependencies\":[{\"branch\":\"master\",\"path\":\"_themes\",\"url\":\"https://github.com/Microsoft/templates.docs.msft\",\"commit_id\":\"be77cfdb101840a69eabbfa9cdb134e565d77113\",\"opbuild.templates.common\":\"1.28.0-alpha-081-g501ae23\"}]}"}