{"breadcrumb_path":"/halfdotnet/toc.json","search.ms_sitename":"Docs","search.ms_docsetname":"halfdotnet","version":0,"locale":"en-us","site_name":"Docs","search.ms_product":"MSDN","depot_name":"MSDN.halfdotnet","ref_skeleton_gitcommit":"https://github.com/TianqiZhang/ECMA2YamlTestRepo/blob/1953e5bf3b3df5c71a159a322e33cc682ce4add9/halfdotnet/System.Reflection.Emit/System.Reflection.Emit.AssemblyBuilder.yml","original_ref_skeleton_git_url":"https://github.com/TianqiZhang/ECMA2YamlTestRepo/blob/migration/halfdotnet/System.Reflection.Emit/System.Reflection.Emit.AssemblyBuilder.yml","open_to_public_contributors":true,"api_name":["System.Reflection.Emit.AssemblyBuilder","System.Reflection.Emit.AssemblyBuilder.AddResourceFile","System.Reflection.Emit.AssemblyBuilder.CodeBase","System.Reflection.Emit.AssemblyBuilder.DefineDynamicAssembly","System.Reflection.Emit.AssemblyBuilder.DefineDynamicModule","System.Reflection.Emit.AssemblyBuilder.DefineResource","System.Reflection.Emit.AssemblyBuilder.DefineUnmanagedResource","System.Reflection.Emit.AssemblyBuilder.DefineVersionInfoResource","System.Reflection.Emit.AssemblyBuilder.EntryPoint","System.Reflection.Emit.AssemblyBuilder.Equals","System.Reflection.Emit.AssemblyBuilder.Evidence","System.Reflection.Emit.AssemblyBuilder.FullName","System.Reflection.Emit.AssemblyBuilder.GetCustomAttributes","System.Reflection.Emit.AssemblyBuilder.GetCustomAttributesData","System.Reflection.Emit.AssemblyBuilder.GetDynamicModule","System.Reflection.Emit.AssemblyBuilder.GetExportedTypes","System.Reflection.Emit.AssemblyBuilder.GetFile","System.Reflection.Emit.AssemblyBuilder.GetFiles","System.Reflection.Emit.AssemblyBuilder.GetHashCode","System.Reflection.Emit.AssemblyBuilder.GetLoadedModules","System.Reflection.Emit.AssemblyBuilder.GetManifestResourceInfo","System.Reflection.Emit.AssemblyBuilder.GetManifestResourceNames","System.Reflection.Emit.AssemblyBuilder.GetManifestResourceStream","System.Reflection.Emit.AssemblyBuilder.GetModule","System.Reflection.Emit.AssemblyBuilder.GetModules","System.Reflection.Emit.AssemblyBuilder.GetName","System.Reflection.Emit.AssemblyBuilder.GetReferencedAssemblies","System.Reflection.Emit.AssemblyBuilder.GetSatelliteAssembly","System.Reflection.Emit.AssemblyBuilder.GetType","System.Reflection.Emit.AssemblyBuilder.GlobalAssemblyCache","System.Reflection.Emit.AssemblyBuilder.HostContext","System.Reflection.Emit.AssemblyBuilder.ImageRuntimeVersion","System.Reflection.Emit.AssemblyBuilder.IsDefined","System.Reflection.Emit.AssemblyBuilder.IsDynamic","System.Reflection.Emit.AssemblyBuilder.Location","System.Reflection.Emit.AssemblyBuilder.ManifestModule","System.Reflection.Emit.AssemblyBuilder.PermissionSet","System.Reflection.Emit.AssemblyBuilder.ReflectionOnly","System.Reflection.Emit.AssemblyBuilder.Save","System.Reflection.Emit.AssemblyBuilder.SecurityRuleSet","System.Reflection.Emit.AssemblyBuilder.SetCustomAttribute","System.Reflection.Emit.AssemblyBuilder.SetEntryPoint","System.Reflection.Emit.AssemblyBuilder.System.Runtime.InteropServices._AssemblyBuilder.GetIDsOfNames","System.Reflection.Emit.AssemblyBuilder.System.Runtime.InteropServices._AssemblyBuilder.GetTypeInfo","System.Reflection.Emit.AssemblyBuilder.System.Runtime.InteropServices._AssemblyBuilder.GetTypeInfoCount","System.Reflection.Emit.AssemblyBuilder.System.Runtime.InteropServices._AssemblyBuilder.Invoke"],"api_location":["mscorlib.dll"],"topic_type":["apiref"],"api_type":["Assembly"],"f1_keywords":["System.Reflection.Emit.AssemblyBuilder","System::Reflection::Emit::AssemblyBuilder","System.Reflection.Emit.AssemblyBuilder.AddResourceFile","System::Reflection::Emit::AssemblyBuilder::AddResourceFile","System.Reflection.Emit.AssemblyBuilder.CodeBase","System::Reflection::Emit::AssemblyBuilder::CodeBase","System.Reflection.Emit.AssemblyBuilder.DefineDynamicAssembly","System::Reflection::Emit::AssemblyBuilder::DefineDynamicAssembly","System.Reflection.Emit.AssemblyBuilder.DefineDynamicModule","System::Reflection::Emit::AssemblyBuilder::DefineDynamicModule","System.Reflection.Emit.AssemblyBuilder.DefineResource","System::Reflection::Emit::AssemblyBuilder::DefineResource","System.Reflection.Emit.AssemblyBuilder.DefineUnmanagedResource","System::Reflection::Emit::AssemblyBuilder::DefineUnmanagedResource","System.Reflection.Emit.AssemblyBuilder.DefineVersionInfoResource","System::Reflection::Emit::AssemblyBuilder::DefineVersionInfoResource","System.Reflection.Emit.AssemblyBuilder.EntryPoint","System::Reflection::Emit::AssemblyBuilder::EntryPoint","System.Reflection.Emit.AssemblyBuilder.Equals","System::Reflection::Emit::AssemblyBuilder::Equals","System.Reflection.Emit.AssemblyBuilder.Evidence","System::Reflection::Emit::AssemblyBuilder::Evidence","System.Reflection.Emit.AssemblyBuilder.FullName","System::Reflection::Emit::AssemblyBuilder::FullName","System.Reflection.Emit.AssemblyBuilder.GetCustomAttributes","System::Reflection::Emit::AssemblyBuilder::GetCustomAttributes","System.Reflection.Emit.AssemblyBuilder.GetCustomAttributesData","System::Reflection::Emit::AssemblyBuilder::GetCustomAttributesData","System.Reflection.Emit.AssemblyBuilder.GetDynamicModule","System::Reflection::Emit::AssemblyBuilder::GetDynamicModule","System.Reflection.Emit.AssemblyBuilder.GetExportedTypes","System::Reflection::Emit::AssemblyBuilder::GetExportedTypes","System.Reflection.Emit.AssemblyBuilder.GetFile","System::Reflection::Emit::AssemblyBuilder::GetFile","System.Reflection.Emit.AssemblyBuilder.GetFiles","System::Reflection::Emit::AssemblyBuilder::GetFiles","System.Reflection.Emit.AssemblyBuilder.GetHashCode","System::Reflection::Emit::AssemblyBuilder::GetHashCode","System.Reflection.Emit.AssemblyBuilder.GetLoadedModules","System::Reflection::Emit::AssemblyBuilder::GetLoadedModules","System.Reflection.Emit.AssemblyBuilder.GetManifestResourceInfo","System::Reflection::Emit::AssemblyBuilder::GetManifestResourceInfo","System.Reflection.Emit.AssemblyBuilder.GetManifestResourceNames","System::Reflection::Emit::AssemblyBuilder::GetManifestResourceNames","System.Reflection.Emit.AssemblyBuilder.GetManifestResourceStream","System::Reflection::Emit::AssemblyBuilder::GetManifestResourceStream","System.Reflection.Emit.AssemblyBuilder.GetModule","System::Reflection::Emit::AssemblyBuilder::GetModule","System.Reflection.Emit.AssemblyBuilder.GetModules","System::Reflection::Emit::AssemblyBuilder::GetModules","System.Reflection.Emit.AssemblyBuilder.GetName","System::Reflection::Emit::AssemblyBuilder::GetName","System.Reflection.Emit.AssemblyBuilder.GetReferencedAssemblies","System::Reflection::Emit::AssemblyBuilder::GetReferencedAssemblies","System.Reflection.Emit.AssemblyBuilder.GetSatelliteAssembly","System::Reflection::Emit::AssemblyBuilder::GetSatelliteAssembly","System.Reflection.Emit.AssemblyBuilder.GetType","System::Reflection::Emit::AssemblyBuilder::GetType","System.Reflection.Emit.AssemblyBuilder.GlobalAssemblyCache","System::Reflection::Emit::AssemblyBuilder::GlobalAssemblyCache","System.Reflection.Emit.AssemblyBuilder.HostContext","System::Reflection::Emit::AssemblyBuilder::HostContext","System.Reflection.Emit.AssemblyBuilder.ImageRuntimeVersion","System::Reflection::Emit::AssemblyBuilder::ImageRuntimeVersion","System.Reflection.Emit.AssemblyBuilder.IsDefined","System::Reflection::Emit::AssemblyBuilder::IsDefined","System.Reflection.Emit.AssemblyBuilder.IsDynamic","System::Reflection::Emit::AssemblyBuilder::IsDynamic","System.Reflection.Emit.AssemblyBuilder.Location","System::Reflection::Emit::AssemblyBuilder::Location","System.Reflection.Emit.AssemblyBuilder.ManifestModule","System::Reflection::Emit::AssemblyBuilder::ManifestModule","System.Reflection.Emit.AssemblyBuilder.PermissionSet","System::Reflection::Emit::AssemblyBuilder::PermissionSet","System.Reflection.Emit.AssemblyBuilder.ReflectionOnly","System::Reflection::Emit::AssemblyBuilder::ReflectionOnly","System.Reflection.Emit.AssemblyBuilder.Save","System::Reflection::Emit::AssemblyBuilder::Save","System.Reflection.Emit.AssemblyBuilder.SecurityRuleSet","System::Reflection::Emit::AssemblyBuilder::SecurityRuleSet","System.Reflection.Emit.AssemblyBuilder.SetCustomAttribute","System::Reflection::Emit::AssemblyBuilder::SetCustomAttribute","System.Reflection.Emit.AssemblyBuilder.SetEntryPoint","System::Reflection::Emit::AssemblyBuilder::SetEntryPoint","System.Reflection.Emit.AssemblyBuilder.System#Runtime#InteropServices#_AssemblyBuilder#GetIDsOfNames","System::Reflection::Emit::AssemblyBuilder::System#Runtime#InteropServices#_AssemblyBuilder#GetIDsOfNames","System.Reflection.Emit.AssemblyBuilder.System#Runtime#InteropServices#_AssemblyBuilder#GetTypeInfo","System::Reflection::Emit::AssemblyBuilder::System#Runtime#InteropServices#_AssemblyBuilder#GetTypeInfo","System.Reflection.Emit.AssemblyBuilder.System#Runtime#InteropServices#_AssemblyBuilder#GetTypeInfoCount","System::Reflection::Emit::AssemblyBuilder::System#Runtime#InteropServices#_AssemblyBuilder#GetTypeInfoCount","System.Reflection.Emit.AssemblyBuilder.System#Runtime#InteropServices#_AssemblyBuilder#Invoke","System::Reflection::Emit::AssemblyBuilder::System#Runtime#InteropServices#_AssemblyBuilder#Invoke"],"dev_langs":["csharp"],"updated_at":"2017-02-16 06:36 AM","document_id":"e9545ca4-6e7b-8a7a-f613-f842976a13d3","layout":"Reference","pagetype":"Reference","title":"AssemblyBuilder class | Microsoft Docs","toc_asset_id":"toc.json","toc_rel":"../toc.json","platforms":["net-11","net-20","netcore-10"],"content_git_url":"","source_url":"","ms.assetid":"System.Reflection.Emit.AssemblyBuilder","canonical_url":"https://ppe.docs.microsoft.com/en-us/halfdotnet/system.reflection.emit/system.reflection.emit.assemblybuilder","is_dynamic_rendering":false,"content_type":"text/html","publish_version":"{\"opbuild.templates.docs\":\"1.28.0-alpha-081-g501ae23\",\"commit_id\":\"c463338a38ee0cf171b48332bb4325e618b23055\",\"branch\":\"migration\",\"opbuild.scripts\":\"1.28.0-alpha-081-g501ae23\",\"opbuild.htmltopdftool\":\"1.28.0-alpha-081-g501ae23\",\"opbuild.gitcontributorinformationresolver\":\"1.28.0-alpha-081-g501ae23\",\"opbuild_service\":\"1.28.81.0\",\"docfx.console\":\"2.13.0-alpha-1199-g3fa481b\",\"opbuild.resolvedependencyconsole\":\"1.28.0-alpha-081-g501ae23\",\"opbuild.schemavalidationconsole\":\"1.28.0-alpha-081-g501ae23\",\"opbuild.redirectionresolver\":\"1.28.0-alpha-081-g501ae23\",\"opbuild.templates.intellisense\":\"1.28.0-alpha-081-g501ae23\",\"dependencies\":[{\"branch\":\"master\",\"path\":\"_themes\",\"url\":\"https://github.com/Microsoft/templates.docs.msft\",\"commit_id\":\"be77cfdb101840a69eabbfa9cdb134e565d77113\",\"opbuild.templates.common\":\"1.28.0-alpha-081-g501ae23\"}]}"}