{"ms.devlang":"csharp","author":"erickson-doug","ms.author":"douge","manager":"douge","breadcrumb_path":"breadcrumb/toc.json","ms.topic":"managed-reference","ms.service":"service-fabric","ms.date":"11/16/2016","search.ms_sitename":"Docs","search.ms_docsetname":"azuredotnet","version":0,"locale":"en-us","site_name":"Docs","search.ms_product":"Azure","depot_name":"Azure.azuredotnet","ref_skeleton_gitcommit":"https://github.com/Azure/azure-docs-sdk-dotnet/blob/8ece26063f2f27414f0bad873159ee6212f3448d/docs-ref-manual/Data/ServiceFabric/System.Fabric.FabricErrorCode.yml","original_ref_skeleton_git_url":"https://github.com/Azure/azure-docs-sdk-dotnet/blob/master/docs-ref-manual/Data/ServiceFabric/System.Fabric.FabricErrorCode.yml","open_to_public_contributors":false,"api_name":["System.Fabric.FabricErrorCode","System.Fabric.FabricErrorCode.Unknown","System.Fabric.FabricErrorCode.InvalidPartitionKey","System.Fabric.FabricErrorCode.UserRoleClientCertificateNotConfigured","System.Fabric.FabricErrorCode.NameAlreadyExists","System.Fabric.FabricErrorCode.ServiceAlreadyExists","System.Fabric.FabricErrorCode.ServiceGroupAlreadyExists","System.Fabric.FabricErrorCode.ApplicationTypeProvisionInProgress","System.Fabric.FabricErrorCode.ApplicationTypeAlreadyExists","System.Fabric.FabricErrorCode.ApplicationAlreadyExists","System.Fabric.FabricErrorCode.NameNotFound","System.Fabric.FabricErrorCode.PropertyNotFound","System.Fabric.FabricErrorCode.PropertyValueEmpty","System.Fabric.FabricErrorCode.ServiceNotFound","System.Fabric.FabricErrorCode.ServiceGroupNotFound","System.Fabric.FabricErrorCode.ApplicationTypeNotFound","System.Fabric.FabricErrorCode.ApplicationTypeInUse","System.Fabric.FabricErrorCode.ApplicationNotFound","System.Fabric.FabricErrorCode.ServiceTypeNotFound","System.Fabric.FabricErrorCode.ServiceManifestNotFound","System.Fabric.FabricErrorCode.NameNotEmpty","System.Fabric.FabricErrorCode.NodeNotFound","System.Fabric.FabricErrorCode.NodeIsUp","System.Fabric.FabricErrorCode.NotPrimary","System.Fabric.FabricErrorCode.NoWriteQuorum","System.Fabric.FabricErrorCode.ReconfigurationPending","System.Fabric.FabricErrorCode.ReplicationQueueFull","System.Fabric.FabricErrorCode.ReplicationOperationTooLarge","System.Fabric.FabricErrorCode.InvalidAtomicGroup","System.Fabric.FabricErrorCode.ServiceOffline","System.Fabric.FabricErrorCode.PartitionNotFound","System.Fabric.FabricErrorCode.ServiceMetadataMismatch","System.Fabric.FabricErrorCode.ServiceAffinityChainNotSupported","System.Fabric.FabricErrorCode.WriteConflict","System.Fabric.FabricErrorCode.ApplicationUpgradeValidationError","System.Fabric.FabricErrorCode.ServiceTypeMismatch","System.Fabric.FabricErrorCode.ServiceTemplateNotFound","System.Fabric.FabricErrorCode.ServiceTypeAlreadyRegistered","System.Fabric.FabricErrorCode.ServiceTypeNotRegistered","System.Fabric.FabricErrorCode.ApplicationUpgradeInProgress","System.Fabric.FabricErrorCode.ApplicationUpdateInProgress","System.Fabric.FabricErrorCode.UpgradeDomainAlreadyCompleted","System.Fabric.FabricErrorCode.FabricVersionNotFound","System.Fabric.FabricErrorCode.FabricVersionInUse","System.Fabric.FabricErrorCode.FabricVersionAlreadyExists","System.Fabric.FabricErrorCode.FabricAlreadyInTargetVersion","System.Fabric.FabricErrorCode.FabricNotUpgrading","System.Fabric.FabricErrorCode.FabricUpgradeInProgress","System.Fabric.FabricErrorCode.FabricUpgradeValidationError","System.Fabric.FabricErrorCode.FabricHealthMaxReportsReached","System.Fabric.FabricErrorCode.FabricHealthStaleReport","System.Fabric.FabricErrorCode.FabricHealthEntityNotFound","System.Fabric.FabricErrorCode.ServiceTooBusy","System.Fabric.FabricErrorCode.CommunicationError","System.Fabric.FabricErrorCode.GatewayNotReachable","System.Fabric.FabricErrorCode.ObjectClosed","System.Fabric.FabricErrorCode.PropertyCheckFailed","System.Fabric.FabricErrorCode.EnumerationCompleted","System.Fabric.FabricErrorCode.ConfigurationSectionNotFound","System.Fabric.FabricErrorCode.ConfigurationParameterNotFound","System.Fabric.FabricErrorCode.InvalidConfiguration","System.Fabric.FabricErrorCode.ImageBuilderValidationError","System.Fabric.FabricErrorCode.ImageBuilderReservedDirectoryError","System.Fabric.FabricErrorCode.ReplicaDoesNotExist","System.Fabric.FabricErrorCode.ProcessDeactivated","System.Fabric.FabricErrorCode.ProcessAborted","System.Fabric.FabricErrorCode.InvalidAddress","System.Fabric.FabricErrorCode.InvalidNameUri","System.Fabric.FabricErrorCode.ValueTooLarge","System.Fabric.FabricErrorCode.DirectoryNotFound","System.Fabric.FabricErrorCode.PathTooLong","System.Fabric.FabricErrorCode.FileNotFound","System.Fabric.FabricErrorCode.NotReady","System.Fabric.FabricErrorCode.OperationTimedOut","System.Fabric.FabricErrorCode.OperationNotComplete","System.Fabric.FabricErrorCode.CodePackageNotFound","System.Fabric.FabricErrorCode.ConfigurationPackageNotFound","System.Fabric.FabricErrorCode.DataPackageNotFound","System.Fabric.FabricErrorCode.EndpointResourceNotFound","System.Fabric.FabricErrorCode.InvalidCredentialType","System.Fabric.FabricErrorCode.InvalidX509FindType","System.Fabric.FabricErrorCode.InvalidX509StoreLocation","System.Fabric.FabricErrorCode.InvalidX509StoreName","System.Fabric.FabricErrorCode.InvalidX509Thumbprint","System.Fabric.FabricErrorCode.InvalidProtectionLevel","System.Fabric.FabricErrorCode.InvalidX509Store","System.Fabric.FabricErrorCode.InvalidSubjectName","System.Fabric.FabricErrorCode.InvalidAllowedCommonNameList","System.Fabric.FabricErrorCode.InvalidCredentials","System.Fabric.FabricErrorCode.DecryptionFailed","System.Fabric.FabricErrorCode.EncryptionFailed","System.Fabric.FabricErrorCode.CorruptedImageStoreObjectFound","System.Fabric.FabricErrorCode.ImageBuilderUnexpectedError","System.Fabric.FabricErrorCode.ImageBuilderTimeoutError","System.Fabric.FabricErrorCode.ImageBuilderAccessDeniedError","System.Fabric.FabricErrorCode.ImageBuilderInvalidMsiFile","System.Fabric.FabricErrorCode.ImageStoreIOException","System.Fabric.FabricErrorCode.ImageStoreAcquireFileLockFailed","System.Fabric.FabricErrorCode.InvalidServiceType","System.Fabric.FabricErrorCode.ApplicationNotUpgrading","System.Fabric.FabricErrorCode.ApplicationAlreadyInTargetVersion","System.Fabric.FabricErrorCode.KeyTooLarge","System.Fabric.FabricErrorCode.KeyNotFound","System.Fabric.FabricErrorCode.SequenceNumberCheckFailed","System.Fabric.FabricErrorCode.TransactionNotActive","System.Fabric.FabricErrorCode.TransactionTooLarge","System.Fabric.FabricErrorCode.MultithreadedTransactionsNotAllowed","System.Fabric.FabricErrorCode.TransactionAborted","System.Fabric.FabricErrorCode.ReliableSessionTransportStartupFailure","System.Fabric.FabricErrorCode.ReliableSessionAlreadyExists","System.Fabric.FabricErrorCode.ReliableSessionCannotConnect","System.Fabric.FabricErrorCode.ReliableSessionManagerExists","System.Fabric.FabricErrorCode.ReliableSessionRejected","System.Fabric.FabricErrorCode.ReliableSessionNotFound","System.Fabric.FabricErrorCode.ReliableSessionQueueEmpty","System.Fabric.FabricErrorCode.ReliableSessionQuotaExceeded","System.Fabric.FabricErrorCode.ReliableSessionServiceFaulted","System.Fabric.FabricErrorCode.ReliableSessionManagerAlreadyListening","System.Fabric.FabricErrorCode.ReliableSessionManagerNotFound","System.Fabric.FabricErrorCode.ReliableSessionManagerNotListening","System.Fabric.FabricErrorCode.ReliableSessionInvalidTargetPartition","System.Fabric.FabricErrorCode.RepairTaskAlreadyExists","System.Fabric.FabricErrorCode.RepairTaskNotFound","System.Fabric.FabricErrorCode.InstanceIdMismatch","System.Fabric.FabricErrorCode.NodeHasNotStoppedYet","System.Fabric.FabricErrorCode.InsufficientClusterCapacity","System.Fabric.FabricErrorCode.ConstraintKeyUndefined","System.Fabric.FabricErrorCode.InvalidPackageSharingPolicy","System.Fabric.FabricErrorCode.PreDeploymentNotAllowed","System.Fabric.FabricErrorCode.InvalidBackupSetting","System.Fabric.FabricErrorCode.InvalidReplicaOperation","System.Fabric.FabricErrorCode.InvalidReplicaStateForReplicaOperation","System.Fabric.FabricErrorCode.MissingFullBackup","System.Fabric.FabricErrorCode.BackupInProgress","System.Fabric.FabricErrorCode.PLBNotReady","System.Fabric.FabricErrorCode.DuplicateServiceNotificationFilterName","System.Fabric.FabricErrorCode.InvalidPartitionOperation","System.Fabric.FabricErrorCode.AlreadyPrimaryReplica","System.Fabric.FabricErrorCode.AlreadySecondaryReplica","System.Fabric.FabricErrorCode.BackupDirectoryNotEmpty","System.Fabric.FabricErrorCode.ForceNotSupportedForReplicaControlOperation","System.Fabric.FabricErrorCode.ConnectionDenied","System.Fabric.FabricErrorCode.ServerAuthenticationFailed","System.Fabric.FabricErrorCode.FabricCannotConnect","System.Fabric.FabricErrorCode.FabricConnectionClosedByRemoteEnd","System.Fabric.FabricErrorCode.FabricMessageTooLarge","System.Fabric.FabricErrorCode.ConstraintNotSatisfied","System.Fabric.FabricErrorCode.FabricEndpointNotFound","System.Fabric.FabricErrorCode.DuplicateWaitObject","System.Fabric.FabricErrorCode.EntryPointNotFound","System.Fabric.FabricErrorCode.DeleteBackupFileFailed","System.Fabric.FabricErrorCode.OperationCanceled","System.Fabric.FabricErrorCode.InvalidTestCommandState","System.Fabric.FabricErrorCode.TestCommandOperationIdAlreadyExists","System.Fabric.FabricErrorCode.ChaosAlreadyRunning","System.Fabric.FabricErrorCode.CMOperationFailed","System.Fabric.FabricErrorCode.FabricDataRootNotFound","System.Fabric.FabricErrorCode.InvalidRestoreData","System.Fabric.FabricErrorCode.DuplicateBackups","System.Fabric.FabricErrorCode.InvalidBackupChain","System.Fabric.FabricErrorCode.StopInProgress","System.Fabric.FabricErrorCode.AlreadyStopped","System.Fabric.FabricErrorCode.NodeIsDown","System.Fabric.FabricErrorCode.NodeTransitionInProgress","System.Fabric.FabricErrorCode.InvalidInstanceId","System.Fabric.FabricErrorCode.InvalidDuration"],"api_location":["System.Fabric.dll"],"topic_type":["apiref"],"api_type":["Assembly"],"f1_keywords":["System.Fabric.FabricErrorCode","System::Fabric::FabricErrorCode","System.Fabric.FabricErrorCode.Unknown","System::Fabric::FabricErrorCode::Unknown","System.Fabric.FabricErrorCode.InvalidPartitionKey","System::Fabric::FabricErrorCode::InvalidPartitionKey","System.Fabric.FabricErrorCode.UserRoleClientCertificateNotConfigured","System::Fabric::FabricErrorCode::UserRoleClientCertificateNotConfigured","System.Fabric.FabricErrorCode.NameAlreadyExists","System::Fabric::FabricErrorCode::NameAlreadyExists","System.Fabric.FabricErrorCode.ServiceAlreadyExists","System::Fabric::FabricErrorCode::ServiceAlreadyExists","System.Fabric.FabricErrorCode.ServiceGroupAlreadyExists","System::Fabric::FabricErrorCode::ServiceGroupAlreadyExists","System.Fabric.FabricErrorCode.ApplicationTypeProvisionInProgress","System::Fabric::FabricErrorCode::ApplicationTypeProvisionInProgress","System.Fabric.FabricErrorCode.ApplicationTypeAlreadyExists","System::Fabric::FabricErrorCode::ApplicationTypeAlreadyExists","System.Fabric.FabricErrorCode.ApplicationAlreadyExists","System::Fabric::FabricErrorCode::ApplicationAlreadyExists","System.Fabric.FabricErrorCode.NameNotFound","System::Fabric::FabricErrorCode::NameNotFound","System.Fabric.FabricErrorCode.PropertyNotFound","System::Fabric::FabricErrorCode::PropertyNotFound","System.Fabric.FabricErrorCode.PropertyValueEmpty","System::Fabric::FabricErrorCode::PropertyValueEmpty","System.Fabric.FabricErrorCode.ServiceNotFound","System::Fabric::FabricErrorCode::ServiceNotFound","System.Fabric.FabricErrorCode.ServiceGroupNotFound","System::Fabric::FabricErrorCode::ServiceGroupNotFound","System.Fabric.FabricErrorCode.ApplicationTypeNotFound","System::Fabric::FabricErrorCode::ApplicationTypeNotFound","System.Fabric.FabricErrorCode.ApplicationTypeInUse","System::Fabric::FabricErrorCode::ApplicationTypeInUse","System.Fabric.FabricErrorCode.ApplicationNotFound","System::Fabric::FabricErrorCode::ApplicationNotFound","System.Fabric.FabricErrorCode.ServiceTypeNotFound","System::Fabric::FabricErrorCode::ServiceTypeNotFound","System.Fabric.FabricErrorCode.ServiceManifestNotFound","System::Fabric::FabricErrorCode::ServiceManifestNotFound","System.Fabric.FabricErrorCode.NameNotEmpty","System::Fabric::FabricErrorCode::NameNotEmpty","System.Fabric.FabricErrorCode.NodeNotFound","System::Fabric::FabricErrorCode::NodeNotFound","System.Fabric.FabricErrorCode.NodeIsUp","System::Fabric::FabricErrorCode::NodeIsUp","System.Fabric.FabricErrorCode.NotPrimary","System::Fabric::FabricErrorCode::NotPrimary","System.Fabric.FabricErrorCode.NoWriteQuorum","System::Fabric::FabricErrorCode::NoWriteQuorum","System.Fabric.FabricErrorCode.ReconfigurationPending","System::Fabric::FabricErrorCode::ReconfigurationPending","System.Fabric.FabricErrorCode.ReplicationQueueFull","System::Fabric::FabricErrorCode::ReplicationQueueFull","System.Fabric.FabricErrorCode.ReplicationOperationTooLarge","System::Fabric::FabricErrorCode::ReplicationOperationTooLarge","System.Fabric.FabricErrorCode.InvalidAtomicGroup","System::Fabric::FabricErrorCode::InvalidAtomicGroup","System.Fabric.FabricErrorCode.ServiceOffline","System::Fabric::FabricErrorCode::ServiceOffline","System.Fabric.FabricErrorCode.PartitionNotFound","System::Fabric::FabricErrorCode::PartitionNotFound","System.Fabric.FabricErrorCode.ServiceMetadataMismatch","System::Fabric::FabricErrorCode::ServiceMetadataMismatch","System.Fabric.FabricErrorCode.ServiceAffinityChainNotSupported","System::Fabric::FabricErrorCode::ServiceAffinityChainNotSupported","System.Fabric.FabricErrorCode.WriteConflict","System::Fabric::FabricErrorCode::WriteConflict","System.Fabric.FabricErrorCode.ApplicationUpgradeValidationError","System::Fabric::FabricErrorCode::ApplicationUpgradeValidationError","System.Fabric.FabricErrorCode.ServiceTypeMismatch","System::Fabric::FabricErrorCode::ServiceTypeMismatch","System.Fabric.FabricErrorCode.ServiceTemplateNotFound","System::Fabric::FabricErrorCode::ServiceTemplateNotFound","System.Fabric.FabricErrorCode.ServiceTypeAlreadyRegistered","System::Fabric::FabricErrorCode::ServiceTypeAlreadyRegistered","System.Fabric.FabricErrorCode.ServiceTypeNotRegistered","System::Fabric::FabricErrorCode::ServiceTypeNotRegistered","System.Fabric.FabricErrorCode.ApplicationUpgradeInProgress","System::Fabric::FabricErrorCode::ApplicationUpgradeInProgress","System.Fabric.FabricErrorCode.ApplicationUpdateInProgress","System::Fabric::FabricErrorCode::ApplicationUpdateInProgress","System.Fabric.FabricErrorCode.UpgradeDomainAlreadyCompleted","System::Fabric::FabricErrorCode::UpgradeDomainAlreadyCompleted","System.Fabric.FabricErrorCode.FabricVersionNotFound","System::Fabric::FabricErrorCode::FabricVersionNotFound","System.Fabric.FabricErrorCode.FabricVersionInUse","System::Fabric::FabricErrorCode::FabricVersionInUse","System.Fabric.FabricErrorCode.FabricVersionAlreadyExists","System::Fabric::FabricErrorCode::FabricVersionAlreadyExists","System.Fabric.FabricErrorCode.FabricAlreadyInTargetVersion","System::Fabric::FabricErrorCode::FabricAlreadyInTargetVersion","System.Fabric.FabricErrorCode.FabricNotUpgrading","System::Fabric::FabricErrorCode::FabricNotUpgrading","System.Fabric.FabricErrorCode.FabricUpgradeInProgress","System::Fabric::FabricErrorCode::FabricUpgradeInProgress","System.Fabric.FabricErrorCode.FabricUpgradeValidationError","System::Fabric::FabricErrorCode::FabricUpgradeValidationError","System.Fabric.FabricErrorCode.FabricHealthMaxReportsReached","System::Fabric::FabricErrorCode::FabricHealthMaxReportsReached","System.Fabric.FabricErrorCode.FabricHealthStaleReport","System::Fabric::FabricErrorCode::FabricHealthStaleReport","System.Fabric.FabricErrorCode.FabricHealthEntityNotFound","System::Fabric::FabricErrorCode::FabricHealthEntityNotFound","System.Fabric.FabricErrorCode.ServiceTooBusy","System::Fabric::FabricErrorCode::ServiceTooBusy","System.Fabric.FabricErrorCode.CommunicationError","System::Fabric::FabricErrorCode::CommunicationError","System.Fabric.FabricErrorCode.GatewayNotReachable","System::Fabric::FabricErrorCode::GatewayNotReachable","System.Fabric.FabricErrorCode.ObjectClosed","System::Fabric::FabricErrorCode::ObjectClosed","System.Fabric.FabricErrorCode.PropertyCheckFailed","System::Fabric::FabricErrorCode::PropertyCheckFailed","System.Fabric.FabricErrorCode.EnumerationCompleted","System::Fabric::FabricErrorCode::EnumerationCompleted","System.Fabric.FabricErrorCode.ConfigurationSectionNotFound","System::Fabric::FabricErrorCode::ConfigurationSectionNotFound","System.Fabric.FabricErrorCode.ConfigurationParameterNotFound","System::Fabric::FabricErrorCode::ConfigurationParameterNotFound","System.Fabric.FabricErrorCode.InvalidConfiguration","System::Fabric::FabricErrorCode::InvalidConfiguration","System.Fabric.FabricErrorCode.ImageBuilderValidationError","System::Fabric::FabricErrorCode::ImageBuilderValidationError","System.Fabric.FabricErrorCode.ImageBuilderReservedDirectoryError","System::Fabric::FabricErrorCode::ImageBuilderReservedDirectoryError","System.Fabric.FabricErrorCode.ReplicaDoesNotExist","System::Fabric::FabricErrorCode::ReplicaDoesNotExist","System.Fabric.FabricErrorCode.ProcessDeactivated","System::Fabric::FabricErrorCode::ProcessDeactivated","System.Fabric.FabricErrorCode.ProcessAborted","System::Fabric::FabricErrorCode::ProcessAborted","System.Fabric.FabricErrorCode.InvalidAddress","System::Fabric::FabricErrorCode::InvalidAddress","System.Fabric.FabricErrorCode.InvalidNameUri","System::Fabric::FabricErrorCode::InvalidNameUri","System.Fabric.FabricErrorCode.ValueTooLarge","System::Fabric::FabricErrorCode::ValueTooLarge","System.Fabric.FabricErrorCode.DirectoryNotFound","System::Fabric::FabricErrorCode::DirectoryNotFound","System.Fabric.FabricErrorCode.PathTooLong","System::Fabric::FabricErrorCode::PathTooLong","System.Fabric.FabricErrorCode.FileNotFound","System::Fabric::FabricErrorCode::FileNotFound","System.Fabric.FabricErrorCode.NotReady","System::Fabric::FabricErrorCode::NotReady","System.Fabric.FabricErrorCode.OperationTimedOut","System::Fabric::FabricErrorCode::OperationTimedOut","System.Fabric.FabricErrorCode.OperationNotComplete","System::Fabric::FabricErrorCode::OperationNotComplete","System.Fabric.FabricErrorCode.CodePackageNotFound","System::Fabric::FabricErrorCode::CodePackageNotFound","System.Fabric.FabricErrorCode.ConfigurationPackageNotFound","System::Fabric::FabricErrorCode::ConfigurationPackageNotFound","System.Fabric.FabricErrorCode.DataPackageNotFound","System::Fabric::FabricErrorCode::DataPackageNotFound","System.Fabric.FabricErrorCode.EndpointResourceNotFound","System::Fabric::FabricErrorCode::EndpointResourceNotFound","System.Fabric.FabricErrorCode.InvalidCredentialType","System::Fabric::FabricErrorCode::InvalidCredentialType","System.Fabric.FabricErrorCode.InvalidX509FindType","System::Fabric::FabricErrorCode::InvalidX509FindType","System.Fabric.FabricErrorCode.InvalidX509StoreLocation","System::Fabric::FabricErrorCode::InvalidX509StoreLocation","System.Fabric.FabricErrorCode.InvalidX509StoreName","System::Fabric::FabricErrorCode::InvalidX509StoreName","System.Fabric.FabricErrorCode.InvalidX509Thumbprint","System::Fabric::FabricErrorCode::InvalidX509Thumbprint","System.Fabric.FabricErrorCode.InvalidProtectionLevel","System::Fabric::FabricErrorCode::InvalidProtectionLevel","System.Fabric.FabricErrorCode.InvalidX509Store","System::Fabric::FabricErrorCode::InvalidX509Store","System.Fabric.FabricErrorCode.InvalidSubjectName","System::Fabric::FabricErrorCode::InvalidSubjectName","System.Fabric.FabricErrorCode.InvalidAllowedCommonNameList","System::Fabric::FabricErrorCode::InvalidAllowedCommonNameList","System.Fabric.FabricErrorCode.InvalidCredentials","System::Fabric::FabricErrorCode::InvalidCredentials","System.Fabric.FabricErrorCode.DecryptionFailed","System::Fabric::FabricErrorCode::DecryptionFailed","System.Fabric.FabricErrorCode.EncryptionFailed","System::Fabric::FabricErrorCode::EncryptionFailed","System.Fabric.FabricErrorCode.CorruptedImageStoreObjectFound","System::Fabric::FabricErrorCode::CorruptedImageStoreObjectFound","System.Fabric.FabricErrorCode.ImageBuilderUnexpectedError","System::Fabric::FabricErrorCode::ImageBuilderUnexpectedError","System.Fabric.FabricErrorCode.ImageBuilderTimeoutError","System::Fabric::FabricErrorCode::ImageBuilderTimeoutError","System.Fabric.FabricErrorCode.ImageBuilderAccessDeniedError","System::Fabric::FabricErrorCode::ImageBuilderAccessDeniedError","System.Fabric.FabricErrorCode.ImageBuilderInvalidMsiFile","System::Fabric::FabricErrorCode::ImageBuilderInvalidMsiFile","System.Fabric.FabricErrorCode.ImageStoreIOException","System::Fabric::FabricErrorCode::ImageStoreIOException","System.Fabric.FabricErrorCode.ImageStoreAcquireFileLockFailed","System::Fabric::FabricErrorCode::ImageStoreAcquireFileLockFailed","System.Fabric.FabricErrorCode.InvalidServiceType","System::Fabric::FabricErrorCode::InvalidServiceType","System.Fabric.FabricErrorCode.ApplicationNotUpgrading","System::Fabric::FabricErrorCode::ApplicationNotUpgrading","System.Fabric.FabricErrorCode.ApplicationAlreadyInTargetVersion","System::Fabric::FabricErrorCode::ApplicationAlreadyInTargetVersion","System.Fabric.FabricErrorCode.KeyTooLarge","System::Fabric::FabricErrorCode::KeyTooLarge","System.Fabric.FabricErrorCode.KeyNotFound","System::Fabric::FabricErrorCode::KeyNotFound","System.Fabric.FabricErrorCode.SequenceNumberCheckFailed","System::Fabric::FabricErrorCode::SequenceNumberCheckFailed","System.Fabric.FabricErrorCode.TransactionNotActive","System::Fabric::FabricErrorCode::TransactionNotActive","System.Fabric.FabricErrorCode.TransactionTooLarge","System::Fabric::FabricErrorCode::TransactionTooLarge","System.Fabric.FabricErrorCode.MultithreadedTransactionsNotAllowed","System::Fabric::FabricErrorCode::MultithreadedTransactionsNotAllowed","System.Fabric.FabricErrorCode.TransactionAborted","System::Fabric::FabricErrorCode::TransactionAborted","System.Fabric.FabricErrorCode.ReliableSessionTransportStartupFailure","System::Fabric::FabricErrorCode::ReliableSessionTransportStartupFailure","System.Fabric.FabricErrorCode.ReliableSessionAlreadyExists","System::Fabric::FabricErrorCode::ReliableSessionAlreadyExists","System.Fabric.FabricErrorCode.ReliableSessionCannotConnect","System::Fabric::FabricErrorCode::ReliableSessionCannotConnect","System.Fabric.FabricErrorCode.ReliableSessionManagerExists","System::Fabric::FabricErrorCode::ReliableSessionManagerExists","System.Fabric.FabricErrorCode.ReliableSessionRejected","System::Fabric::FabricErrorCode::ReliableSessionRejected","System.Fabric.FabricErrorCode.ReliableSessionNotFound","System::Fabric::FabricErrorCode::ReliableSessionNotFound","System.Fabric.FabricErrorCode.ReliableSessionQueueEmpty","System::Fabric::FabricErrorCode::ReliableSessionQueueEmpty","System.Fabric.FabricErrorCode.ReliableSessionQuotaExceeded","System::Fabric::FabricErrorCode::ReliableSessionQuotaExceeded","System.Fabric.FabricErrorCode.ReliableSessionServiceFaulted","System::Fabric::FabricErrorCode::ReliableSessionServiceFaulted","System.Fabric.FabricErrorCode.ReliableSessionManagerAlreadyListening","System::Fabric::FabricErrorCode::ReliableSessionManagerAlreadyListening","System.Fabric.FabricErrorCode.ReliableSessionManagerNotFound","System::Fabric::FabricErrorCode::ReliableSessionManagerNotFound","System.Fabric.FabricErrorCode.ReliableSessionManagerNotListening","System::Fabric::FabricErrorCode::ReliableSessionManagerNotListening","System.Fabric.FabricErrorCode.ReliableSessionInvalidTargetPartition","System::Fabric::FabricErrorCode::ReliableSessionInvalidTargetPartition","System.Fabric.FabricErrorCode.RepairTaskAlreadyExists","System::Fabric::FabricErrorCode::RepairTaskAlreadyExists","System.Fabric.FabricErrorCode.RepairTaskNotFound","System::Fabric::FabricErrorCode::RepairTaskNotFound","System.Fabric.FabricErrorCode.InstanceIdMismatch","System::Fabric::FabricErrorCode::InstanceIdMismatch","System.Fabric.FabricErrorCode.NodeHasNotStoppedYet","System::Fabric::FabricErrorCode::NodeHasNotStoppedYet","System.Fabric.FabricErrorCode.InsufficientClusterCapacity","System::Fabric::FabricErrorCode::InsufficientClusterCapacity","System.Fabric.FabricErrorCode.ConstraintKeyUndefined","System::Fabric::FabricErrorCode::ConstraintKeyUndefined","System.Fabric.FabricErrorCode.InvalidPackageSharingPolicy","System::Fabric::FabricErrorCode::InvalidPackageSharingPolicy","System.Fabric.FabricErrorCode.PreDeploymentNotAllowed","System::Fabric::FabricErrorCode::PreDeploymentNotAllowed","System.Fabric.FabricErrorCode.InvalidBackupSetting","System::Fabric::FabricErrorCode::InvalidBackupSetting","System.Fabric.FabricErrorCode.InvalidReplicaOperation","System::Fabric::FabricErrorCode::InvalidReplicaOperation","System.Fabric.FabricErrorCode.InvalidReplicaStateForReplicaOperation","System::Fabric::FabricErrorCode::InvalidReplicaStateForReplicaOperation","System.Fabric.FabricErrorCode.MissingFullBackup","System::Fabric::FabricErrorCode::MissingFullBackup","System.Fabric.FabricErrorCode.BackupInProgress","System::Fabric::FabricErrorCode::BackupInProgress","System.Fabric.FabricErrorCode.PLBNotReady","System::Fabric::FabricErrorCode::PLBNotReady","System.Fabric.FabricErrorCode.DuplicateServiceNotificationFilterName","System::Fabric::FabricErrorCode::DuplicateServiceNotificationFilterName","System.Fabric.FabricErrorCode.InvalidPartitionOperation","System::Fabric::FabricErrorCode::InvalidPartitionOperation","System.Fabric.FabricErrorCode.AlreadyPrimaryReplica","System::Fabric::FabricErrorCode::AlreadyPrimaryReplica","System.Fabric.FabricErrorCode.AlreadySecondaryReplica","System::Fabric::FabricErrorCode::AlreadySecondaryReplica","System.Fabric.FabricErrorCode.BackupDirectoryNotEmpty","System::Fabric::FabricErrorCode::BackupDirectoryNotEmpty","System.Fabric.FabricErrorCode.ForceNotSupportedForReplicaControlOperation","System::Fabric::FabricErrorCode::ForceNotSupportedForReplicaControlOperation","System.Fabric.FabricErrorCode.ConnectionDenied","System::Fabric::FabricErrorCode::ConnectionDenied","System.Fabric.FabricErrorCode.ServerAuthenticationFailed","System::Fabric::FabricErrorCode::ServerAuthenticationFailed","System.Fabric.FabricErrorCode.FabricCannotConnect","System::Fabric::FabricErrorCode::FabricCannotConnect","System.Fabric.FabricErrorCode.FabricConnectionClosedByRemoteEnd","System::Fabric::FabricErrorCode::FabricConnectionClosedByRemoteEnd","System.Fabric.FabricErrorCode.FabricMessageTooLarge","System::Fabric::FabricErrorCode::FabricMessageTooLarge","System.Fabric.FabricErrorCode.ConstraintNotSatisfied","System::Fabric::FabricErrorCode::ConstraintNotSatisfied","System.Fabric.FabricErrorCode.FabricEndpointNotFound","System::Fabric::FabricErrorCode::FabricEndpointNotFound","System.Fabric.FabricErrorCode.DuplicateWaitObject","System::Fabric::FabricErrorCode::DuplicateWaitObject","System.Fabric.FabricErrorCode.EntryPointNotFound","System::Fabric::FabricErrorCode::EntryPointNotFound","System.Fabric.FabricErrorCode.DeleteBackupFileFailed","System::Fabric::FabricErrorCode::DeleteBackupFileFailed","System.Fabric.FabricErrorCode.OperationCanceled","System::Fabric::FabricErrorCode::OperationCanceled","System.Fabric.FabricErrorCode.InvalidTestCommandState","System::Fabric::FabricErrorCode::InvalidTestCommandState","System.Fabric.FabricErrorCode.TestCommandOperationIdAlreadyExists","System::Fabric::FabricErrorCode::TestCommandOperationIdAlreadyExists","System.Fabric.FabricErrorCode.ChaosAlreadyRunning","System::Fabric::FabricErrorCode::ChaosAlreadyRunning","System.Fabric.FabricErrorCode.CMOperationFailed","System::Fabric::FabricErrorCode::CMOperationFailed","System.Fabric.FabricErrorCode.FabricDataRootNotFound","System::Fabric::FabricErrorCode::FabricDataRootNotFound","System.Fabric.FabricErrorCode.InvalidRestoreData","System::Fabric::FabricErrorCode::InvalidRestoreData","System.Fabric.FabricErrorCode.DuplicateBackups","System::Fabric::FabricErrorCode::DuplicateBackups","System.Fabric.FabricErrorCode.InvalidBackupChain","System::Fabric::FabricErrorCode::InvalidBackupChain","System.Fabric.FabricErrorCode.StopInProgress","System::Fabric::FabricErrorCode::StopInProgress","System.Fabric.FabricErrorCode.AlreadyStopped","System::Fabric::FabricErrorCode::AlreadyStopped","System.Fabric.FabricErrorCode.NodeIsDown","System::Fabric::FabricErrorCode::NodeIsDown","System.Fabric.FabricErrorCode.NodeTransitionInProgress","System::Fabric::FabricErrorCode::NodeTransitionInProgress","System.Fabric.FabricErrorCode.InvalidInstanceId","System::Fabric::FabricErrorCode::InvalidInstanceId","System.Fabric.FabricErrorCode.InvalidDuration","System::Fabric::FabricErrorCode::InvalidDuration"],"dev_langs":["csharp","vb"],"updated_at":"2016-12-19 07:26 AM","document_id":"6ce5afdb-1078-69a9-7dc9-d234fdde1ef7","layout":"Reference","pagetype":"Reference","title":"FabricErrorCode enum | Microsoft Docs","description":"Defines error codes that can be associated with a .\n","toc_asset_id":"toc.json","toc_rel":"toc.json","content_git_url":"","source_url":"https://msazure.visualstudio.com/DefaultCollection/One/_git/WindowsFabric?path=src/prod/src/managed/Api/src/System/Fabric/FabricErrorCode.cs&version=GBdevelop&line=12","ms.assetid":"System.Fabric.FabricErrorCode","canonical_url":"https://docs.microsoft.com/en-us/dotnet/api/system.fabric.fabricerrorcode","is_dynamic_rendering":false,"content_type":"text/html","publish_version":"{\"opbuild.templates.docs\":\"1.27.4\",\"commit_id\":\"8418579ac82f551781057a21da3984b1f6fa5910\",\"branch\":\"master\",\"opbuild.scripts\":\"1.27.4\",\"opbuild.htmltopdftool\":\"1.27.4\",\"opbuild.gitcontributorinformationresolver\":\"1.27.4\",\"opbuild_service\":\"1.27.361.0\",\"docfx.console\":\"2.12.1\",\"opbuild.resolvedependencyconsole\":\"1.27.4\",\"opbuild.schemavalidationconsole\":\"1.27.4\",\"opbuild.redirectionresolver\":\"1.27.4\",\"opbuild.templates.intellisense\":\"1.27.4\",\"dependencies\":[{\"branch\":\"master\",\"path\":\"_themes\",\"url\":\"https://github.com/Microsoft/templates.docs.msft\",\"commit_id\":\"7d3ef1a51554bb393cfbe59160c498316c9c2dc3\",\"opbuild.templates.common\":\"1.27.4\"}]}"}